flexaidpy/__init__.py
flexaidpy/bin/FlexAID.exe
flexaidpy/deps/AMINO.def
flexaidpy/deps/AMINO12.def
flexaidpy/deps/AMINO26.def
flexaidpy/deps/AMINO8.def
flexaidpy/deps/Lovell_LIB.dat
flexaidpy/deps/M6_cons_3.dat
flexaidpy/deps/MC_st0r5.2_6.dat
flexaidpy/deps/nrg_mat_BEST_011912.dat
flexaidpy/deps/nrg_mat_BEST_012012.dat
flexaidpy/deps/NUCLEOTIDES.def
flexaidpy/deps/NUCLEOTIDES12.def
flexaidpy/deps/NUCLEOTIDES26.def
flexaidpy/deps/NUCLEOTIDES8.def
flexaidpy/deps/rotobs.lst
flexaidpy/deps/scr_bin.dat
flexaidpy/deps/scr_mat.dat
flexaidpy/deps/SYBYL_emat.dat
flexaidpy/FlexAID_wrapper.py
flexaidpy/write_config.py
flexaidpy/write_ga.py
flexaid_py-1.0.5.dist-info/METADATA
flexaid_py-1.0.5.dist-info/WHEEL
flexaid_py-1.0.5.dist-info/RECORD
